highlambder/__init__.py
highlambder/core.py
highlambder-0.1.3.dist-info/licenses/LICENSE
highlambder-0.1.3.dist-info/METADATA
highlambder-0.1.3.dist-info/WHEEL
highlambder-0.1.3.dist-info/top_level.txt
highlambder-0.1.3.dist-info/RECORD
