Metadata-Version: 2.4
Name: highlambder
Version: 0.1.3
Summary: Syntactic Sugar for Lambda Expressions
Author-email: Dario Colombotto <dario.colombotto@outlook.com>
License: MIT
Project-URL: Homepage, https://github.com/colomb8/highlambder
License-File: LICENSE
Dynamic: license-file
